makim/__init__.py
makim/__main__.py
makim/cli/__init__.py
makim/cli/auto_generator.py
makim/cli/config.py
makim/cli/cron_handlers.py
makim/console.py
makim/core.py
makim/logs.py
makim/py.typed
makim/scheduler.py
makim/schema.json
makim/task_logging.py
makim-1.27.0.dist-info/LICENSE
makim-1.27.0.dist-info/METADATA
makim-1.27.0.dist-info/WHEEL
makim-1.27.0.dist-info/entry_points.txt
makim-1.27.0.dist-info/RECORD
