Metadata-Version: 2.3
Name: makim
Version: 1.27.0
Summary: A tool that helps organize and simplify helper commands using YAML configuration
License: BSD 3 Clause
Author: Ivan Ogasawara
Author-email: ivan.ogasawara@gmail.com
Requires-Python: >=3.9,<4
Classifier: License :: Other/Proprietary License
Classifier: Programming Language :: Python :: 3
Classifier: Programming Language :: Python :: 3.9
Classifier: Programming Language :: Python :: 3.10
Classifier: Programming Language :: Python :: 3.11
Classifier: Programming Language :: Python :: 3.12
Classifier: Programming Language :: Python :: 3.13
Requires-Dist: apscheduler (>=3.11.0,<4.0.0)
Requires-Dist: fuzzywuzzy (>=0.18.0)
Requires-Dist: jinja2 (>=2.0)
Requires-Dist: jsonschema (>=4)
Requires-Dist: paramiko (>=3.5.0)
Requires-Dist: python-dotenv (>=0.21.1)
Requires-Dist: python-levenshtein (>=0.23.0)
Requires-Dist: pyyaml (>=5.0)
Requires-Dist: rich (>=10.11.0)
Requires-Dist: shellingham (>=1.5.4)
Requires-Dist: sqlalchemy (>=2.0.37,<3.0.0)
Requires-Dist: typer (>=0.9.0)
Requires-Dist: types-paramiko (>=3.5.0)
Requires-Dist: xhell (>=0.2.0)
Requires-Dist: xonsh (>=0.15.0)
